{"cameraMode":{"drawMode":0,"name":"Shaded","section":"Shading Mode"},"sceneLighting":true,"audioPlay":false,"sceneViewState":{"showFog":true,"showMaterialUpdate":false,"showSkybox":true,"showFlares":true,"showImageEffects":true,"showParticleSystems":true},"in2DMode":false,"pivot":{"x":4.988938808441162,"y":30.997583389282228,"z":-7.211291790008545},"rotation":{"x":0.08988502621650696,"y":-0.011061437427997589,"z":0.0010067890398204327,"w":0.9959268569946289},"size":0.37688183784484866,"orthographic":false}